tara_mvp/__init__.py
tara_mvp/_brand.py
tara_mvp/cli.py
tara_mvp/attacks/__init__.py
tara_mvp/attacks/generator.py
tara_mvp/attacks/patterns.py
tara_mvp/attacks/scenarios.py
tara_mvp/attacks/simulator.py
tara_mvp/core/__init__.py
tara_mvp/core/coherence.py
tara_mvp/core/firewall.py
tara_mvp/core/layers.py
tara_mvp/core/scale_freq.py
tara_mvp/data/__init__.py
tara_mvp/data/bci_nodes.py
tara_mvp/data/brain_regions.py
tara_mvp/data/moabb_adapter.py
tara_mvp/data/openbci_adapter.py
tara_mvp/data/export/__init__.py
tara_mvp/neurosecurity/__init__.py
tara_mvp/neurosecurity/integration.py
tara_mvp/nsam/__init__.py
tara_mvp/nsam/alerts.py
tara_mvp/nsam/detector.py
tara_mvp/nsam/events.py
tara_mvp/nsam/monitor.py
tara_mvp/nsam/rules.py
tara_mvp/persistence/__init__.py
tara_mvp/simulation/__init__.py
tara_mvp/simulation/engine/__init__.py
tara_mvp/simulation/engine/events.py
tara_mvp/simulation/engine/recorder.py
tara_mvp/simulation/engine/simulator.py
tara_mvp/simulation/networks/__init__.py
tara_mvp/simulation/networks/base.py
tara_mvp/simulation/networks/layered.py
tara_mvp/simulation/networks/recurrent.py
tara_mvp/simulation/networks/small_world.py
tara_mvp/simulation/neurons/__init__.py
tara_mvp/simulation/neurons/adaptive_lif.py
tara_mvp/simulation/neurons/base.py
tara_mvp/simulation/neurons/hodgkin_huxley.py
tara_mvp/simulation/neurons/izhikevich.py
tara_mvp/simulation/neurons/lif.py
tara_mvp/simulation/synapses/__init__.py
tara_mvp/simulation/synapses/base.py
tara_mvp/simulation/synapses/chemical.py
tara_mvp/simulation/synapses/electrical.py
tara_mvp/simulation/synapses/stdp.py
tara_mvp/tests/__init__.py
tara_mvp/tests/conftest.py
tara_mvp/tests/test_core.py
tara_mvp/tests/test_data.py
tara_mvp/tests/test_moabb_adapter.py
tara_mvp/ui/__init__.py
tara_mvp/ui/app.py
tara_mvp/ui/styles.py
tara_mvp/ui/widgets/__init__.py
tara_mvp/visualization/__init__.py
tara_mvp/visualization/components/__init__.py
tara_mvp/visualization/components/brain_topology.py
oni_tara-0.8.1.dist-info/METADATA
oni_tara-0.8.1.dist-info/WHEEL
oni_tara-0.8.1.dist-info/entry_points.txt
oni_tara-0.8.1.dist-info/licenses/LICENSE
oni_tara-0.8.1.dist-info/RECORD
