Metadata-Version: 2.4
Name: oni-tara
Version: 0.8.1
Summary: TARA - Telemetry Analysis & Response Automation. A neural security platform for brain-computer interfaces with Kohno threat taxonomy and BCI privacy filtering.
Project-URL: Homepage, https://github.com/qikevinl/ONI
Project-URL: Documentation, https://github.com/qikevinl/ONI/tree/main/MAIN/tara-neural-security-platform
Project-URL: Repository, https://github.com/qikevinl/ONI
Project-URL: Issues, https://github.com/qikevinl/ONI/issues
Author-email: "Kevin L. Qi" <kevin@example.com>
License: Apache-2.0
License-File: LICENSE
Keywords: attack-simulation,bci,bci-privacy,blue-team,brain-computer-interface,coherence,cybersecurity,defensive-security,erp-filtering,kohno,neural-networks,neural-security,neural-signal-assurance,neural-telemetry,neuroscience,neurosecurity,nsam,oni-framework,threat-detection
Classifier: Development Status :: 4 - Beta
Classifier: Intended Audience :: Developers
Classifier: Intended Audience :: Science/Research
Classifier: License :: OSI Approved :: Apache Software License
Classifier: Operating System :: OS Independent
Classifier: Programming Language :: Python :: 3
Classifier: Programming Language :: Python :: 3.9
Classifier: Programming Language :: Python :: 3.10
Classifier: Programming Language :: Python :: 3.11
Classifier: Programming Language :: Python :: 3.12
Classifier: Topic :: Scientific/Engineering :: Bio-Informatics
Classifier: Topic :: Scientific/Engineering :: Medical Science Apps.
Classifier: Topic :: Security
Classifier: Topic :: Software Development :: Libraries :: Python Modules
Requires-Python: >=3.9
Requires-Dist: numpy>=1.21.0
Requires-Dist: scipy>=1.7.0
Provides-Extra: dev
Requires-Dist: black>=23.0.0; extra == 'dev'
Requires-Dist: mypy>=1.0.0; extra == 'dev'
Requires-Dist: pytest-cov>=4.0.0; extra == 'dev'
Requires-Dist: pytest>=7.0.0; extra == 'dev'
Requires-Dist: ruff>=0.1.0; extra == 'dev'
Provides-Extra: full
Requires-Dist: matplotlib>=3.5.0; extra == 'full'
Requires-Dist: mne>=1.0.0; extra == 'full'
Requires-Dist: moabb>=0.5.0; extra == 'full'
Requires-Dist: pandas>=1.4.0; extra == 'full'
Requires-Dist: plotly>=5.17.0; extra == 'full'
Requires-Dist: scikit-learn>=1.0.0; extra == 'full'
Requires-Dist: streamlit>=1.28.0; extra == 'full'
Provides-Extra: moabb
Requires-Dist: mne>=1.0.0; extra == 'moabb'
Requires-Dist: moabb>=0.5.0; extra == 'moabb'
Requires-Dist: pandas>=1.4.0; extra == 'moabb'
Requires-Dist: scikit-learn>=1.0.0; extra == 'moabb'
Provides-Extra: simulation
Requires-Dist: matplotlib>=3.5.0; extra == 'simulation'
Requires-Dist: pandas>=1.4.0; extra == 'simulation'
Provides-Extra: ui
Requires-Dist: plotly>=5.17.0; extra == 'ui'
Requires-Dist: streamlit>=1.28.0; extra == 'ui'
